tkvue/__init__.py
tkvue/tests/__init__.py
tkvue/tests/preloader.gif
tkvue/tests/python_icon.png
tkvue/tests/test_tkvue.py
tkvue-2.1.6.dist-info/LICENSE
tkvue-2.1.6.dist-info/METADATA
tkvue-2.1.6.dist-info/WHEEL
tkvue-2.1.6.dist-info/entry_points.txt
tkvue-2.1.6.dist-info/top_level.txt
tkvue-2.1.6.dist-info/RECORD
