Metadata-Version: 2.1
Name: tkvue
Version: 2.1.6
Summary: Declarative Tkinter UI using makup language with reactive data binding
Home-page: https://gitlab.com/ikus-soft/tkvue
Author: IKUS Software inc.
Author-email: support@ikus-soft.com
Maintainer: Patrik Dufresne
Maintainer-email: patrik@ikus-soft.com
License: LGPLv3
Classifier: Development Status :: 4 - Beta
Classifier: Environment :: X11 Applications
Classifier: Environment :: Win32 (MS Windows)
Classifier: Intended Audience :: Developers
Classifier: Intended Audience :: End Users/Desktop
Classifier: License :: OSI Approved :: GNU Lesser General Public License v3 (LGPLv3)
Classifier: Operating System :: MacOS
Classifier: Operating System :: Microsoft :: Windows
Classifier: Operating System :: POSIX :: Linux
Classifier: Programming Language :: Python :: 3
Classifier: Programming Language :: Python :: 3.6
Classifier: Programming Language :: Python :: 3.7
Classifier: Programming Language :: Python :: 3.8
Classifier: Programming Language :: Python :: 3.9
Classifier: Programming Language :: Python :: 3.10
Classifier: Topic :: Software Development :: User Interfaces
Requires-Python: <4,>=3.6
License-File: LICENSE
